<?xml version="1.0" encoding="UTF-8"?>
<blocks>
  <block id="d8115c3a0d36958b2dc6371f0596bd31" category="summary">Cloud Manager에서 StorageGRID 시스템을 발견한 후, 백업 및 데이터 동기화에 NetApp의 데이터 서비스를 StorageGRID와 함께 사용할 수 있습니다.</block>
  <block id="4d59e76f3a0fb15954592256790b7f7e" category="doc">StorageGRID에서 NetApp 데이터 서비스 사용</block>
  <block id="99211d9a136453b70c5891be3c9f4a44" category="paragraph">Cloud Manager에서 StorageGRID 시스템을 검색하고 나면 NetApp의 데이터 서비스를 사용하여 백업 및 데이터 동기화를 수행할 수 있습니다.</block>
  <block id="3822be2497c1c1e2e76ff4863e2d510e" category="list-text">클라우드 백업 * 을 사용하여 사내 ONTAP 시스템의 데이터를 NetApp StorageGRID 시스템의 오브젝트 스토리지로 백업할 수 있습니다.</block>
  <block id="7e995f90ad07a7b6c4bbd3ebeea051bb" category="paragraph">시작하려면 Canvas로 이동하여 StorageGRID 작업 환경에서 온-프레미스 ONTAP 작업 환경을 끌어다 놓습니다.</block>
  <block id="a4304a5e5ad0523cd1e2516efcbb04ea" category="inline-link">사내 ONTAP 데이터를 StorageGRID에 백업하는 방법에 대해 자세히 알아보십시오</block>
  <block id="5848e24b55c702b7cc486314cd78f6dc" category="paragraph"><block ref="5848e24b55c702b7cc486314cd78f6dc" category="inline-link-rx"></block></block>
  <block id="c2c9861dbf50fae669de81ff19a8e714" category="list-text">Cloud Sync * 를 사용하여 StorageGRID 시스템과 데이터를 동기화하십시오.</block>
  <block id="d295ee26072b39ec669dd814d31c9a1e" category="paragraph">시작하려면 Canvas로 이동하여 대상 작업 환경에 소스 작업 환경을 끌어다 놓습니다. StorageGRID는 소스 또는 타겟이 될 수 있습니다.</block>
  <block id="c9e8b2e7aec1baa65efcbe84dfc9d0ed" category="inline-link">Cloud Sync에 대해 자세히 알아보십시오</block>
  <block id="fcea636cb0627956ef5da173e7e82e53" category="paragraph"><block ref="fcea636cb0627956ef5da173e7e82e53" category="inline-link-rx"></block></block>
  <block id="2cafdb15b131b36e54b11aecf95de3eb" category="summary">Cloud Manager에서 StorageGRID 시스템을 관리하는 새로운 기능에 대해 알아보십시오.</block>
  <block id="a39b0065ec636bbdd671213be9d343f4" category="doc">StorageGRID 관리의 새로운 기능</block>
  <block id="f7ba76d5c9beab0576f118a6254843e9" category="section-title">2022년 9월 18일</block>
  <block id="dc8bb8905a6984d0c45a4ada9e618ace" category="section-title">StorageGRID 지원</block>
  <block id="2e9322f9d5b6c0a3474db4758b049aa0" category="paragraph">이제 Cloud Manager에서 직접 StorageGRID 시스템을 검색할 수 있습니다. StorageGRID을 발견하여 하이브리드 멀티 클라우드 전체의 데이터를 완벽하게 파악할 수 있습니다.</block>
  <block id="20ef63d96310e418922174cda82700cf" category="summary">Cloud Manager를 사용하면 사내 환경에서 StorageGRID 시스템을 검색할 수 있습니다. StorageGRID 클러스터를 Cloud Manager에 추가하면 하이브리드 멀티 클라우드 전체의 데이터를 완벽하게 파악할 수 있습니다.</block>
  <block id="d85b01f001ee16ebd8eb1917c739d824" category="doc">StorageGRID 시스템에 대해 알아보십시오</block>
  <block id="a252e3759b53abf6ef51975e3f291cf6" category="paragraph">Cloud Manager를 사용하면 사내 환경에서 StorageGRID 시스템을 검색할 수 있습니다. StorageGRID 시스템을 Cloud Manager에 추가하면 하이브리드 멀티 클라우드 전체의 데이터를 완벽하게 파악할 수 있습니다.</block>
  <block id="a711863513c11f3a6d86294acc7be0ba" category="list-title">무엇을 &amp;#8217;필요로 할거야</block>
  <block id="031f2c2a8e686936eab9e36e2d0d5c66" category="list-text">StorageGRID 시스템에 대한 네트워크 연결을 통해 클라우드 공급자 또는 사내에 설치된 커넥터.</block>
  <block id="013d29d39e390d6b894eaf54e5b91328" category="inline-link">커넥터 및 커넥터 작성 방법에 대해 자세히 알아보십시오</block>
  <block id="8604e02ef9173d1fcb905c94b3e7744f" category="paragraph"><block ref="8604e02ef9173d1fcb905c94b3e7744f" category="inline-link-rx"></block></block>
  <block id="8ed6fea4723099b9cd21d8f577ab8fb6" category="list-text">관리 노드의 도메인 이름 또는 IP 주소입니다.</block>
  <block id="cdf740c7139af2d388c8083334061fa1" category="list-text">관리 노드에 대한 관리자 자격 증명입니다.</block>
  <block id="f3a29486bed19a90f2da6d007818b427" category="list-title">단계</block>
  <block id="f7724c6cf62e295d95285d154eaf1a06" category="list-text">Canvas에서 * 작업 환경 추가 * 를 클릭하고 * 온-프레미스 * 를 선택합니다.</block>
  <block id="7fd958d2cabd0884d2f06017cf1f56c4" category="list-text">StorageGRID * 를 선택하고 * 다음 * 을 클릭합니다.</block>
  <block id="2f799a76b51c894f217a81de4e75abc1" category="list-text">메시지가 표시되면 연결선을 만듭니다.</block>
  <block id="b5047ecbe29388d4251d2e7ffe1d3437" category="paragraph">자세한 내용은 위의 링크를 참조하십시오.</block>
  <block id="f50edfcfb42c3810a2ab7cdb0717f656" category="list-text">StorageGRID 클러스터 세부 정보 _ 페이지에서 admin 노드의 도메인 이름 또는 IP 주소, 노드의 자격 증명을 입력한 다음 * 추가 * 를 클릭합니다.</block>
  <block id="b692c7e41f214f1934d82e1fb8c34551" category="inline-image-macro">관리자 노드의 도메인 이름 또는 IP 주소와 자격 증명을 입력하는 StorageGRID 클러스터 세부 정보 페이지를 보여 주는 스크린샷</block>
  <block id="6f4e41dd41fcea233053f2ba61b3e93c" category="paragraph"><block ref="6f4e41dd41fcea233053f2ba61b3e93c" category="inline-image-macro-rx" type="image"></block></block>
  <block id="0a9a77891b8e70c43c8027941f8f8c47" category="paragraph">Cloud Manager는 StorageGRID 시스템을 검색하여 Canvas의 작업 환경으로 추가합니다.</block>
  <block id="7751122cf2f78c5c38ebae8a86a13558" category="inline-image-macro">Cloud Manager Canvas에서 StorageGRID 작업 환경을 보여 주는 스크린샷</block>
  <block id="ad05e85ca472a43c0c711e7a9a42f891" category="paragraph"><block ref="ad05e85ca472a43c0c711e7a9a42f891" category="inline-image-macro-rx" type="image"></block></block>
  <block id="0bf8a233feaff9e97e741d5e88905db3" category="summary">StorageGRID 시스템을 발견한 후 용량 분포 및 관련 알림, 노드 및 테넌트에 대한 세부 정보를 볼 수 있습니다.</block>
  <block id="c20219c45cfba3fdfc2396d8aa96c143" category="doc">StorageGRID 시스템을 봅니다</block>
  <block id="d3303815967fe0fbdde9310a5ce39f60" category="list-text">Canvas에서 보려는 StorageGRID 작업 환경의 이름을 두 번 클릭합니다.</block>
  <block id="847dbe3b8f852409d936c93bfb31177b" category="list-text">StorageGRID 시스템에 대한 자세한 내용을 보려면 탭을 선택하십시오.</block>
  <block id="8cee006c52b25ffa341e9665d1f36032" category="list-text">* 개요 *: 시스템의 용량 분포(사용된 용량 및 사용 가능한 용량), 시스템 알림, 노드 및 테넌트 수 등에 대한 상세 정보 보기</block>
  <block id="ae796f15b5a3a00075075c6caecd9cfc" category="inline-image-macro">StorageGRID 작업 환경의 개요 탭에 대한 스크린샷</block>
  <block id="364310a3a6741380a3adc72411a52d65" category="paragraph"><block ref="364310a3a6741380a3adc72411a52d65" category="inline-image-macro-rx" type="image"></block></block>
  <block id="7a78715e6a36fa2dcf6896248ccc058c" category="list-text">* 경고 *: 활성 경고, 해결된 경고 및 해제된 경고를 포함하는 시스템 경고 요약입니다.</block>
  <block id="88a1a574aabf262882af454484c4f44f" category="list-text">* 노드 *: 관리 노드, API 게이트웨이 노드 및 스토리지 노드에 대한 세부 정보 여기에는 사용된 오브젝트 데이터, 사용된 오브젝트 메타데이터 및 CPU 사용량 백분율이 포함됩니다.</block>
  <block id="62fac2d9fde29d69903d60965ae80e36" category="inline-image-macro">StorageGRID 작업 환경의 노드 탭 스크린샷</block>
  <block id="320c3346e3e8a511e898b63029025992" category="paragraph"><block ref="320c3346e3e8a511e898b63029025992" category="inline-image-macro-rx" type="image"></block></block>
  <block id="91106c0a9a8679958f2d935850e42f7e" category="list-text">* Tenants *: 사용된 논리적 공간, 할당량, 할당량, 객체 수를 포함하는 테넌트에 대한 주요 세부 정보.</block>
  <block id="e51c4414740e4f4ba2e02bd06c8d9e88" category="inline-image-macro">StorageGRID 작업 환경의 Tenants 탭 스크린샷</block>
  <block id="c99b6babe545010e47410b64d23e3096" category="paragraph"><block ref="c99b6babe545010e47410b64d23e3096" category="inline-image-macro-rx" type="image"></block></block>
  <block id="d41d8cd98f00b204e9800998ecf8427e" category="summary"></block>
  <block id="30d965eef5ba25c6b9998ae38270b43e" category="doc">법적 고지</block>
  <block id="e9c44bbfd795a5d63d74c6a77afee70d" category="paragraph">법적 고지 사항은 저작권 선언, 상표, 특허 등에 대한 액세스를 제공합니다.</block>
  <block id="6016a2b341113bf496b719905398ecd2" category="section-title">저작권</block>
  <block id="09e95b77ffe81fe465a83ba99efad5c8" category="paragraph"><block ref="09e95b77ffe81fe465a83ba99efad5c8" category="inline-link-rx"></block></block>
  <block id="126a02652da6de02962cf1b654fd6376" category="section-title">상표</block>
  <block id="c4ce4761e466527d26b3e3d5ed1006fd" category="paragraph">NetApp, NetApp 로고, NetApp 상표 페이지에 나열된 마크는 NetApp Inc.의 상표입니다. 기타 회사 및 제품 이름은 해당 소유자의 상표일 수 있습니다.</block>
  <block id="7aa531e9acfe2b98e34d2c92fe9846ff" category="paragraph"><block ref="7aa531e9acfe2b98e34d2c92fe9846ff" category="inline-link-rx"></block></block>
  <block id="be89498d2f8a22ce47c02ba9795fe2af" category="section-title">특허</block>
  <block id="d0b19d36be2c5f16e9aef46c8a452d3d" category="paragraph">NetApp 소유 특허 목록은 다음 사이트에서 확인할 수 있습니다.</block>
  <block id="d7f1fbcf9ce4e42f705add574d262b2c" category="paragraph"><block ref="d7f1fbcf9ce4e42f705add574d262b2c" category="inline-link-rx"></block></block>
  <block id="56c34c6410dd45c5cec44149ad0ce037" category="section-title">개인 정보 보호 정책</block>
  <block id="fc248f74f5e36542f7f5627b8610e9a3" category="paragraph"><block ref="fc248f74f5e36542f7f5627b8610e9a3" category="inline-link-rx"></block></block>
  <block id="c0227cef6f07a8cd2ac72f2945b031aa" category="section-title">오픈 소스</block>
  <block id="9b73989307c1975dfa4d5e1581e4afe8" category="paragraph">통지 파일은 NetApp 소프트웨어에 사용된 타사의 저작권 및 라이센스에 대한 정보를 제공합니다.</block>
  <block id="4940124e8487cb4ea36f1511a195cf66" category="inline-link-macro">Cloud Manager 3.9에 대한 고지 사항</block>
  <block id="c069fcc68c5dfa73ccc99924c836cae9" category="list-text"><block ref="c069fcc68c5dfa73ccc99924c836cae9" category="inline-link-macro-rx"></block></block>
  <block id="e2c2c17af726ff1e98fd9d46febbbf74" category="summary">Cloud Manager에서 더 이상 StorageGRID 작업 환경을 관리하지 않으려는 경우 해당 환경을 제거합니다.</block>
  <block id="eabf36128e3f33d63b2921cfcf0f1162" category="doc">StorageGRID 작업 환경을 제거합니다</block>
  <block id="258cc430ad542cf521e937f5e65ac8f3" category="paragraph">작업 환경을 제거해도 StorageGRID 시스템에는 영향을 주지 않습니다. Cloud Manager에서 언제든지 다시 검색할 수 있습니다.</block>
  <block id="e2196663fe8ae041909eecbbe019e082" category="list-text">Canvas에서 StorageGRID 작업 환경의 이름을 두 번 클릭합니다.</block>
  <block id="b787a2a1998073d68d40ce850ecb5c3e" category="list-text">메뉴 아이콘을 클릭하고 * 작업 공간에서 제거 * 를 선택합니다.</block>
  <block id="9ae507836de7475bf9902e01733fe556" category="inline-image-macro">작업 환경의 오른쪽 위 메뉴에서 사용할 수 있는 작업 공간에서 제거 옵션의 스크린샷</block>
  <block id="c8e6868d5b00caa06a19765007794f02" category="paragraph"><block ref="c8e6868d5b00caa06a19765007794f02" category="inline-image-macro-rx" type="image"></block></block>
  <block id="40b851aafab82c78484c46169f816fd2" category="list-text">확인하려면 * 제거 * 를 클릭합니다.</block>
  <block id="ce21e7ae4271271294ccbf54c8fd6864" category="summary">NetApp은 다양한 방법으로 Cloud Manager를 지원합니다. 기술 자료(KB) 기사 및 커뮤니티 포럼과 같은 광범위한 무료 셀프 지원 옵션이 24x7 제공됩니다. 지원 등록에는 웹 티켓팅을 통한 원격 기술 지원이 포함됩니다.</block>
  <block id="fabfc25ef8996fd90836e58a4c0b26b6" category="doc">도움을 받으십시오</block>
  <block id="51719eefc68685ac0e2a11057a44b8be" category="paragraph">NetApp은 다양한 방법으로 Cloud Manager 및 클라우드 서비스를 지원합니다. 기술 자료(KB) 기사 및 커뮤니티 포럼과 같은 광범위한 무료 셀프 지원 옵션이 24x7 제공됩니다. 지원 등록에는 웹 티켓팅을 통한 원격 기술 지원이 포함됩니다.</block>
  <block id="07d41912a6ab6b97216f8cf89e93205c" category="section-title">자체 지원</block>
  <block id="5e4b821a1a82558dead1ef6961e90666" category="paragraph">이 옵션은 하루 24시간, 주 7일 동안 무료로 사용할 수 있습니다.</block>
  <block id="19111351b69b6b15668130b38b7f6038" category="inline-link">기술 자료</block>
  <block id="fd6bb4fa1ad0caeedd6782d92cc54ea3" category="list-text"><block ref="fd6bb4fa1ad0caeedd6782d92cc54ea3" category="inline-link-rx"></block></block>
  <block id="76b571fb5edea1c1994fa0ff01f7b1e2" category="paragraph">Cloud Manager 기술 자료를 검색하여 문제를 해결할 수 있는 유용한 문서를 찾습니다.</block>
  <block id="14526abd8bda5af347775025cd5342cf" category="inline-link">커뮤니티</block>
  <block id="410fdb9caa9c64da2ff3f88f4836960d" category="list-text"><block ref="410fdb9caa9c64da2ff3f88f4836960d" category="inline-link-rx"></block></block>
  <block id="7f3490343cad8dc3bfdb72dd5d957e8d" category="paragraph">Cloud Manager 커뮤니티에 가입하여 진행 중인 토론을 팔로우하거나 새 토론을 만들어보십시오.</block>
  <block id="5b6cf869265c13af8566f192b4ab3d2a" category="list-text">문서화</block>
  <block id="3c313458d6e15dd2c4336e47118d0a8f" category="paragraph">현재 보고 있는 Cloud Manager 문서입니다.</block>
  <block id="80b1b0d2b1ebf2b3cba2d25759801afd" category="list-text">mailto:ng-cloudmanager-feedback@netapp.com [피드백 이메일]</block>
  <block id="bff60abbc46aceed0f73a3a4f6cfb123" category="paragraph">저희는 귀하의 의견을 소중하게 생각합니다. 클라우드 관리자 개선에 도움이 되는 피드백을 제출해 주십시오.</block>
  <block id="0659d428df833a806e29e65e632d380a" category="section-title">NetApp 지원</block>
  <block id="c91b5a63849b8d2db01014ed33192735" category="paragraph">위의 자체 지원 옵션 외에도 NetApp 지원 엔지니어와 협력하여 지원을 활성화한 이후의 모든 문제를 해결할 수 있습니다.</block>
  <block id="6c08c57e382a25a778455184cd9b1a4a" category="list-text">Cloud Manager에서 * 도움말 &gt; 지원 * 을 클릭합니다.</block>
  <block id="f5052c65917d7341726235d4d4941461" category="list-text">기술 지원 아래에서 사용 가능한 옵션 중 하나를 선택합니다.</block>
  <block id="bece28b158ab337d9ed24b00d7d02cc7" category="list-text">NetApp 기술 지원을 위한 전화 번호를 찾으려면 * 문의하다</block>
  <block id="efe81cff8e6f47ec59ef94167b76bf5a" category="list-text">문제 열기 * 를 클릭하고 옵션 중 하나를 선택한 다음 * 보내기 * 를 클릭합니다.</block>
  <block id="cbb1040836732e478409dacf7e45171a" category="paragraph">NetApp 담당자가 귀하의 케이스를 검토하고 곧 다시 귀하에 연락을 드릴 것입니다.</block>
  <block id="3c10116b37b407ac79092a38ffb292e4" category="summary">NetApp 기술 지원으로 지원 케이스를 생성하기 전에 NetApp Support 사이트 계정을 Cloud Manager에 추가한 다음 지원을 위해 등록해야 합니다.</block>
  <block id="42748df9eaa0be17ddc5cc1593cf57ab" category="doc">지원을 위해 등록하십시오</block>
  <block id="aeaeee19a7c393222e407a525cf01991" category="section-title">NSS 계정을 추가합니다</block>
  <block id="de2241fea60d98698faaa196ff73ee80" category="paragraph">지원 대시보드를 이용하면 모든 NetApp Support 사이트 계정을 단일 위치에서 추가 및 관리할 수 있습니다.</block>
  <block id="5be2593b5948f30a15179a32daa73ee2" category="inline-link">1인 등록</block>
  <block id="14b05cf61f1aba58d38b393e69b69538" category="list-text">아직 NetApp Support 사이트 계정이 없는 경우<block ref="0a8e82436ea73fe635862cfba3acf101" category="inline-link-rx"></block>.</block>
  <block id="0046efb3377274ff3215d4b30269809e" category="list-text">Cloud Manager 콘솔의 오른쪽 상단에서 도움말 아이콘을 클릭하고 * 지원 * 을 선택합니다.</block>
  <block id="b50f0a46135bcb7083b1f2f82032fc26" category="inline-image-macro">도움말 메뉴의 스크린샷으로, 여기에서 지원은 첫 번째 옵션입니다</block>
  <block id="868d9aa88f16ea923af1d15eac5d2647" category="paragraph"><block ref="868d9aa88f16ea923af1d15eac5d2647" category="inline-image-macro-rx" type="image"></block></block>
  <block id="d17d6b5dafebab6b7659da8850737e70" category="list-text">NSS 관리 &gt; NSS 계정 추가 * 를 클릭합니다.</block>
  <block id="8aaf101e623c543c7eef3c65f6233366" category="list-text">메시지가 표시되면 * 계속 * 을 클릭하여 Microsoft 로그인 페이지로 리디렉션됩니다.</block>
  <block id="19d089db572ee6a1e154a0c9c9e57bfd" category="paragraph">NetApp은 Microsoft Azure Active Directory를 지원 및 라이선싱과 관련된 인증 서비스의 ID 공급자로 사용합니다.</block>
  <block id="465ec6d5eafa3524c948c99d8bfcd306" category="list-text">로그인 페이지에서 인증 프로세스를 수행할 수 있도록 NetApp Support 사이트의 등록 이메일 주소와 암호를 제공합니다.</block>
  <block id="f5fb4199485234c409525f430b737010" category="paragraph">이 작업을 수행하면 Cloud Manager에서 NSS 계정을 사용할 수 있습니다.</block>
  <block id="b4c6a2f33e7b2a38495546b8d5cd8e84" category="paragraph">참고 계정은 고객 수준 계정이어야 합니다(게스트 또는 임시 계정이 아님).</block>
  <block id="fc65ebd4739f2f8ca46062a8280faea9" category="section-title">계정을 등록하여 지원을 받을 수 있습니다</block>
  <block id="3e080914efe0d0ca025439fbb68d437f" category="paragraph">지원 등록은 지원 대시보드의 Cloud Manager에서 가능합니다.</block>
  <block id="fb07bf6b7698dbe934b8b2164d915484" category="list-text">Resources * 탭에서 * Register for Support * 를 클릭합니다.</block>
  <block id="392fb0270d0d84dbc3fdf8c67da1e5ad" category="list-text">등록할 NSS 자격 증명을 선택한 다음 * 등록 * 을 클릭합니다.</block>
  <block id="9268f95494e3c64b00b2b6e1664c2b8b" category="summary">Cloud Manager를 통해 StorageGRID 시스템을 검색하여 하이브리드 멀티 클라우드 전체의 데이터를 완벽하게 파악할 수 있습니다.</block>
  <block id="3778f3873debfe11e2ace6bb6af1e417" category="doc">StorageGRID 설명서</block>
  <block id="67d5dc044866a0ff55b817d754d94a3e" category="sidebar">StorageGRID 문서</block>
  <block id="7d0ee6fed10d3d4e5c9ee496729ab519" category="sidebar">릴리스 정보</block>
  <block id="be11c74c1dd7f307bb80183a90dc2067" category="sidebar">시작하십시오</block>
  <block id="f8fe3d533b3c8ec77c886cdbfcbd8c60" category="sidebar">StorageGRID 시스템에 대해 알아보십시오</block>
  <block id="a6ba2d89122672398b70094e4effce77" category="sidebar">StorageGRID 시스템 관리</block>
  <block id="d4fe66ba55f1e103d1e1ef42d9901921" category="sidebar">StorageGRID 시스템을 제거합니다</block>
  <block id="0adc03eac86772ad2c75c8f140be417e" category="sidebar">지식 및 지원</block>
  <block id="5a48514fa915876d588438500b09c18f" category="sidebar">StorageGRID를 제거합니다</block>
  <block id="ab066b3292d8ab61ef3b5c77169cdd19" category="sidebar">추가 정보</block>
  <block id="64ddc745342a0d340d406b6521027e76" category="sidebar">Cloud Manager 외부의 관리를 위한 StorageGRID 문서</block>
  <block id="813011e2103649bb71f124adedcc10ea" category="sidebar">블로그 커뮤니티</block>
  <block id="dd490b81914dd945601e442a41cb4222" category="sidebar">NetApp 커뮤니티</block>
  <block id="ff6c37cbc252e306a6b4e390ec13cbc1" category="sidebar">Cloud Central 블로그</block>
  <block id="ad203e818e0c9d7f42f1c260b33875f3" category="sidebar">클라우드 웨비나</block>
  <block id="7ff191df90fac0fa94ab5c2b5101a5e9" category="sidebar">모든 Cloud Manager 설명서</block>
</blocks>